am/__init__.py
am/py.typed
am/cli/__init__.py
am/cli/__main__.py
am/cli/options.py
am/cli/version.py
am/config/__init__.py
am/config/build_parameters.py
am/config/material.py
am/config/mcp.py
am/config/mesh_parameters.py
am/config/process_map.py
am/config/cli/__init__.py
am/config/cli/__main__.py
am/config/cli/build_parameters.py
am/config/cli/material.py
am/config/cli/mesh_parameters.py
am/config/cli/process_map.py
am/data/__init__.py
am/data/mcp/agent.md
am/data/parts/README.md
am/data/parts/overhang.STL
am/mcp/__init__.py
am/mcp/__main__.py
am/mcp/install.py
am/mcp/types.py
am/mcp/uninstall.py
am/mcp/utils.py
am/mcp/cli/__init__.py
am/mcp/cli/__main__.py
am/mcp/cli/development.py
am/mcp/cli/install.py
am/mcp/cli/uninstall.py
am/simulator/__init__.py
am/simulator/cli/measure_melt_pool_dimensions.py
am/simulator/cli/process_map.py
am/simulator/cli/residual_heat.py
am/simulator/cli/run_layer.py
am/simulator/cli/visualize.py
am/simulator/mcp/__init__.py
am/simulator/mcp/process_map.py
am/simulator/mcp/run_layer.py
am/simulator/mcp/visualize.py
am/simulator/solver/__init__.py
am/simulator/solver/diffuse.py
am/simulator/solver/gaussian.py
am/simulator/solver/layer.py
am/simulator/solver/measure.py
am/simulator/solver/mesh.py
am/simulator/solver/types.py
am/simulator/solver/analytical/__init__.py
am/simulator/solver/analytical/eagar_tsai.py
am/simulator/solver/analytical/rosenthal.py
am/simulator/solver/models/__init__.py
am/simulator/solver/models/melt_pool_dimensions.py
am/simulator/solver/models/solver_layer.py
am/simulator/solver/models/solver_segment.py
am/simulator/tool/process_map/__init__.py
am/simulator/tool/process_map/models/__init__.py
am/simulator/tool/process_map/models/process_map.py
am/simulator/tool/process_map/models/process_map_data_point.py
am/simulator/tool/process_map/models/process_map_parameter.py
am/simulator/tool/process_map/models/process_map_parameter_range.py
am/simulator/tool/process_map/models/process_map_plot_data.py
additive_manufacturing-0.0.20.dist-info/METADATA
additive_manufacturing-0.0.20.dist-info/WHEEL
additive_manufacturing-0.0.20.dist-info/entry_points.txt
additive_manufacturing-0.0.20.dist-info/top_level.txt
additive_manufacturing-0.0.20.dist-info/RECORD
