Metadata-Version: 2.4
Name: additive-manufacturing
Version: 0.0.20
Summary: Package for additive manufacturing related tools.
Author-email: Peter Pak <ppak10@gmail.com>
Project-URL: Homepage, https://github.com/ppak10/additive-manufacturing
Project-URL: Issues, https://github.com/ppak10/additive-manufacturing/issues
Requires-Python: >=3.10
Requires-Dist: imageio>=2.37.0
Requires-Dist: jax>=0.6.2
Requires-Dist: matplotlib>=3.10.3
Requires-Dist: mcp>=1.12.3
Requires-Dist: msgpack>=1.1.2
Requires-Dist: pint>=0.24.4
Requires-Dist: pintdantic>=0.0.4
Requires-Dist: pydantic>=2.11.7
Requires-Dist: pygcode>=0.2.1
Requires-Dist: rich>=14.0.0
Requires-Dist: scipy>=1.15.3
Requires-Dist: tqdm>=4.67.1
Requires-Dist: trimesh[easy]>=4.9.0
Requires-Dist: typer>=0.16.0
Requires-Dist: workspace-agent>=0.1.9
Provides-Extra: cuda12
Requires-Dist: jax[cuda12]>=0.6.2; extra == "cuda12"
